<?xml version='1.0' encoding='UTF-8'?>
<package version="0.0.0" uuid="taichi-5ba226">
 <names>
  <name lang="en_US">demo_thai_chi</name>
 </names>
 <supportedLanguages>
  <language>en_US</language>
  <language>de_DE</language>
 </supportedLanguages>
 <descriptionLanguages>
  <language>en_US</language>
  <language>de_DE</language>
 </descriptionLanguages>
 <contents>
  <behaviorContent path="behavior_1">
   <userRequestable/>
   <nature>interactive</nature>
   <permissions/>
  </behaviorContent>
 </contents>
</package>
